ocrCraftModel4uts/__init__.py
ocrCraftModel4uts/data/craft_mlt_25k.pth
ocrCraftModel4uts-1.0.1.dist-info/METADATA
ocrCraftModel4uts-1.0.1.dist-info/WHEEL
ocrCraftModel4uts-1.0.1.dist-info/top_level.txt
ocrCraftModel4uts-1.0.1.dist-info/RECORD
